biosites/__init__.py
biosites/base.py
biosites/cli.py
biosites/extractor.py
biosites/models.py
biosites/redirect_handler.py
biosites/extractors/__init__.py
biosites/extractors/biosite.py
biosites/extractors/inpock.py
biosites/extractors/instabio.py
biosites/extractors/linkbio_co.py
biosites/extractors/linkme.py
biosites/extractors/linktree.py
biosites/extractors/litlink.py
biosites/extractors/littly.py
biosites-1.0.0.dist-info/METADATA
biosites-1.0.0.dist-info/WHEEL
biosites-1.0.0.dist-info/entry_points.txt
biosites-1.0.0.dist-info/licenses/LICENSE
biosites-1.0.0.dist-info/RECORD
