Metadata-Version: 2.4
Name: biosites
Version: 1.0.0
Summary: Extract links from bio link services like Linktree
License: MIT License
License-File: LICENSE
Requires-Python: >=3.10
Requires-Dist: aiohttp>=3.9.0
Requires-Dist: pybase64>=1.3.0
Requires-Dist: pydantic>=2.0.0
Requires-Dist: selectolax>=0.3.0
